pure_safetensors/__init__.py
pure_safetensors/__main__.py
pure_safetensors/adapter.py
pure_safetensors/exc.py
pure_safetensors/mmap.py
pure_safetensors/numpy.py
pure_safetensors/safetensors.py
pure_safetensors/util.py
pure_safetensors/ext/__init__.py
pure_safetensors/ext/torch.py
pure_safetensors-0.3.2.dist-info/METADATA
pure_safetensors-0.3.2.dist-info/WHEEL
pure_safetensors-0.3.2.dist-info/top_level.txt
pure_safetensors-0.3.2.dist-info/RECORD
