Metadata-Version: 2.1
Name: pure-safetensors
Version: 0.3.2
Summary: Pure-Python safetensors
Home-page: UNKNOWN
Author: Eduard Christian Dumitrescu
Author-email: eduard.c.dumitrescu@gmail.com
License: MIT
Platform: UNKNOWN
Classifier: Programming Language :: Python :: 3
Classifier: License :: OSI Approved :: MIT License
Classifier: Operating System :: OS Independent
Requires-Dist: attrs
Requires-Dist: marshmallow
Requires-Dist: sortedcollections
